build/lib/mfd_code_quality/__init__.py
build/lib/mfd_code_quality/log_formatter.py
build/lib/mfd_code_quality/mfd_code_quality.py
build/lib/mfd_code_quality/utils.py
build/lib/mfd_code_quality/code_standard/__init__.py
build/lib/mfd_code_quality/code_standard/checks.py
build/lib/mfd_code_quality/code_standard/configure.py
build/lib/mfd_code_quality/code_standard/formats.py
build/lib/mfd_code_quality/coverage/__init__.py
build/lib/mfd_code_quality/coverage/consts.py
build/lib/mfd_code_quality/coverage/utils.py
build/lib/mfd_code_quality/testing_utilities/__init__.py
build/lib/mfd_code_quality/testing_utilities/consts.py
build/lib/mfd_code_quality/testing_utilities/import_tests.py
build/lib/mfd_code_quality/testing_utilities/system_tests.py
build/lib/mfd_code_quality/testing_utilities/unit_tests.py
mfd_code_quality/__init__.py
mfd_code_quality/log_formatter.py
mfd_code_quality/mfd_code_quality.py
mfd_code_quality/utils.py
mfd_code_quality/code_standard/__init__.py
mfd_code_quality/code_standard/checks.py
mfd_code_quality/code_standard/configure.py
mfd_code_quality/code_standard/formats.py
mfd_code_quality/code_standard/generic_pyproject.txt
mfd_code_quality/code_standard/generic_ruff.txt
mfd_code_quality/code_standard/config_per_module/mfd_berta_wrappers_mev_package_installer_ruff.toml
mfd_code_quality/code_standard/config_per_module/mfd_connect_ruff.toml
mfd_code_quality/code_standard/config_per_module/mfd_ixchariot_ruff.toml
mfd_code_quality/code_standard/config_per_module/mfd_module_template_pyproject.toml
mfd_code_quality/code_standard/config_per_module/mfd_module_template_ruff.toml
mfd_code_quality/code_standard/config_per_module/pytest_mfd_plugin_template_pyproject.toml
mfd_code_quality/code_standard/config_per_module/pytest_mfd_plugin_template_ruff.toml
mfd_code_quality/code_standard/config_per_module/test_project_template_pyproject.toml
mfd_code_quality/code_standard/config_per_module/test_project_template_ruff.toml
mfd_code_quality/coverage/__init__.py
mfd_code_quality-1.3.0.dist-info/licenses/AUTHORS.md
mfd_code_quality-1.3.0.dist-info/licenses/LICENSE.md
mfd_code_quality-1.3.0.dist-info/METADATA
mfd_code_quality-1.3.0.dist-info/WHEEL
mfd_code_quality-1.3.0.dist-info/entry_points.txt
mfd_code_quality-1.3.0.dist-info/top_level.txt
mfd_code_quality-1.3.0.dist-info/RECORD
