Metadata-Version: 2.4
Name: mfd-code-quality
Version: 1.3.0
Summary: Module for a code quality related scripts.
Project-URL: Homepage, https://github.com/intel/mfd
Project-URL: Repository, https://github.com/intel/mfd-code-quality
Project-URL: Issues, https://github.com/intel/mfd-code-quality/issues
Project-URL: Changelog, https://github.com/intel/mfd-code-quality/blob/main/CHANGELOG.md
Requires-Python: <3.14,>=3.10
License-File: LICENSE.md
License-File: AUTHORS.md
Requires-Dist: pytest<9,>=7.2.1
Requires-Dist: pytest-cov~=5.0.0
Requires-Dist: pytest-xdist~=3.6.1
Requires-Dist: coverage~=7.3.0
Requires-Dist: diff-cover<9,>=8.0.3
Requires-Dist: ansicolors~=1.1
Requires-Dist: ruff==0.4.7
Requires-Dist: setuptools
Dynamic: license-file
